Workbook

Sheet Documentation
A1: HOUSEHOLD PORTFOLIO ENGINE — DOCUMENTATION & USER GUIDE
A3: WHY THIS SPREADSHEET EXISTS
B4: This workbook manages a two-bucket, decumulation-phase retirement income strategy built to protect the household from Sequence-of-Returns Risk (SRR) -- the danger that a market downturn early in retirement forces the sale of depreciated stocks to cover monthly living expenses, permanently damaging the portfolio's ability to recover. The strategy rests on three ideas, described below.
B5: 1. The TSP G Fund as a "free lunch" cash vault. By law, the G Fund earns the yield of intermediate- to long-term Treasuries while never losing principal value and staying instantly liquid. It serves as the household's operating cash account -- monthly bills are paid straight out of it, so equities are never sold to cover routine expenses.
B6: 2. A dynamic Refill Engine, not a fixed withdrawal rate. Instead of a static 4%-rule, this workbook tracks a real-growth hurdle (COLA layered on a fixed real-growth baseline) year over year. When actual household wealth clears that hurdle, it's safe to harvest equity gains and roll them back into the G Fund to top the shield back up. When wealth falls short, all equity sales freeze and the G Fund alone absorbs spending, giving stocks time to recover.
B7: 3. Asset location by account. Safe, fixed-income assets are deliberately concentrated in accounts built for stability (the TSP G Fund, a spouse's workplace plan), while private IRAs hold the aggressive growth positions and serve as Roth-conversion conduits -- keeping each spouse's accounts doing the job they're best suited for.
A9: HOW THE FOUR TABS WORK TOGETHER
B10: Documentation (this tab) -- Motivation, how-to, a quarterly checklist, the color legend, and a glossary. Nothing here feeds any formula; it's for the humans using the sheet.
B11: Variables_And_Log -- Where you log the two things that change constantly: the actual Social Security/Federal COLA each year, and every month's actual TSP -> checking payment. Everything else on this tab is a formula built from those two inputs.
B12: Account_Tracker -- A snapshot of every account's live balance, updated by hand whenever you check statements (aim for at least quarterly). This is the single source of truth for household net worth that every other tab's formulas reference.
B13: The_Refill_Engine -- The decision-making tab. The Quarterly Refill Engine table is the headline output -- each quarter it tells you how much (if anything) to move from a private pre-tax account into the TSP G Fund. Below that, the Annual SRR Hurdle Model is the strategic gauge that decides GOOD vs. POOR for the year, and the Emergency Liquidity Protocol tells you, in a full-blown crisis, exactly which account to draw from next.
A15: YOUR QUARTERLY CHECKLIST
A16: 1. | B16: Update Account_Tracker with current balances from your statements.
A17: 2. | B17: Confirm Variables_And_Log has this quarter's three monthly TSP payments logged.
A18: 3. | B18: Open The_Refill_Engine and find this quarter's row in the Quarterly Refill Engine table.
A19: 4. | B19: Check the "Recommended Transfer This Quarter" cell. If it's $0, do nothing -- the shield is intact or the market hasn't cleared its hurdle yet.
A20: 5. | B20: If it's a positive number, execute a pre-tax rollover of that amount from your Conversion Conduit (Traditional IRA) into the TSP G Fund.
A21: 6. | B21: Log whatever you actually transferred in the "Actual Transferred" column, even if it matches the recommendation exactly -- leaving it blank makes the sheet assume the recommendation happened.
A22: 7. | B22: If the TSP G Fund is ever fully drawn down, check the Emergency Liquidity Protocol block for the next-dollar priority order.
A24: COLOR LEGEND
B25: Pale yellow -- type your own numbers here.
B26: White (no fill) -- a formula; please leave it alone.
B27: Ice blue -- a computed summary or headline total.
B28: Green (Emergency Liquidity Protocol only) -- the TSP G Fund shield is active.
B29: Yellow (Emergency Liquidity Protocol only) -- the G Fund is exhausted; drawing from the cash buffer.
B30: Red (Emergency Liquidity Protocol only) -- both cash shields are exhausted; the household is in an emergency-liquidation stage.
A32: GLOSSARY
A33: Term | B33: Definition
A34: COLA | B34: The federal Cost-of-Living Adjustment, applied annually to Social Security/federal retirement benefits.
A35: Hurdle Rate | B35: The minimum real (inflation-adjusted) growth rate the portfolio needs to clear to be considered "on track" -- COLA layered on a fixed real-growth baseline.
A36: W_t / W_q | B36: Total dollar outflows (withdrawals) for a given year (t) or quarter (q).
A37: P_track | B37: The simulated target portfolio value that the household's actual wealth is measured against each year.
A38: SRR | B38: Sequence-of-Returns Risk -- the risk that a downturn early in retirement forces permanent sale of depreciated assets.
A39: TSP G Fund | B39: The federal Thrift Savings Plan's government-securities fund: principal-protected, instantly liquid, and the household's operating cash vault.
A40: Safety Anchor | B40: The G Fund cash buffer this engine tries to maintain, expressed as a percentage of total net worth (set on The_Refill_Engine).
A41: Conduit | B41: A Traditional IRA used as a pass-through for pre-tax rollovers back into the TSP.
A42: Rollover | B42: A pre-tax transfer of funds between retirement accounts (e.g. Traditional IRA to TSP) that doesn't trigger a taxable distribution.
A43: Allocation Mix | B43: Each account's share of total household net worth, shown on Account_Tracker.

Sheet Variables_And_Log
A1: HOUSEHOLD VARIABLE LOG — ANNUAL HURDLE INPUTS & MONTHLY TSP → CHECKING PAYMENT LOG (2026-2035)
A2: Date / Year | B2: Actual Federal COLA (C_i) | C2: Rule of Four Hurdle Baseline | D2: Total Annual Hurdle Rate | E2: Total Annual Outflows (W_t) | F2: Jan | G2: Feb | H2: Mar | I2: Apr | J2: May | K2: Jun | L2: Jul | M2: Aug | N2: Sep | O2: Oct | P2: Nov | Q2: Dec
A3: 2026 | B3: 0.026 | C3: 0.02 | D3: =(1+B3)*(1+C3) | E3: =SUM(F3:Q3)
A4: 2027 | C4: 0.02 | D4: =(1+B4)*(1+C4) | E4: =SUM(F4:Q4)
A5: 2028 | C5: 0.02 | D5: =(1+B5)*(1+C5) | E5: =SUM(F5:Q5)
A6: 2029 | C6: 0.02 | D6: =(1+B6)*(1+C6) | E6: =SUM(F6:Q6)
A7: 2030 | C7: 0.02 | D7: =(1+B7)*(1+C7) | E7: =SUM(F7:Q7)
A8: 2031 | C8: 0.02 | D8: =(1+B8)*(1+C8) | E8: =SUM(F8:Q8)
A9: 2032 | C9: 0.02 | D9: =(1+B9)*(1+C9) | E9: =SUM(F9:Q9)
A10: 2033 | C10: 0.02 | D10: =(1+B10)*(1+C10) | E10: =SUM(F10:Q10)
A11: 2034 | C11: 0.02 | D11: =(1+B11)*(1+C11) | E11: =SUM(F11:Q11)
A12: 2035 | C12: 0.02 | D12: =(1+B12)*(1+C12) | E12: =SUM(F12:Q12)
A14: Notes: Seed 2026 COLA is set; enter 2027-2035 COLA as it is announced each fall. Log each month's actual TSP -> checking payment in columns F:Q as it is set or changes -- Total Annual Outflows (E) sums automatically. If a payment amount changes mid-year, just overwrite that month's cell going forward.
A15: Legend: pale-yellow cells are yours to type into; white cells hold formulas -- please don't overwrite them.

Sheet Account_Tracker
A1: Asset Pool | B1: Custodian / Platform | C1: Live Balance | D1: Allocation Mix
A2: Your Pre-Tax Account | B2: TSP G Fund | C2: 100000 | D2: =C2/$C$9
A3: Your Conversion Conduit | B3: Private Traditional IRA | C3: 100000 | D3: =C3/$C$9
A4: Your Tax-Free Growth | B4: Private Roth IRA | C4: 100000 | D4: =C4/$C$9
A5: Spouse's Tax-Free Growth | B5: Private Roth IRA | C5: 100000 | D5: =C5/$C$9
A6: Spouse's Safe Pre-Tax Account | B6: Current Employer 403b (Active + Reverse Rollover) | C6: 100000 | D6: =C6/$C$9
A7: Spouse's Conversion Conduit | B7: Private Traditional IRA | C7: 100000 | D7: =C7/$C$9
A8: Short-Term Liquidity | B8: Merrill Edge Cash Buffer | C8: 100000 | D8: =C8/$C$9
A9: Total Household Net Worth | C9: =SUM(C2:C8) | D9: =C9/C9
A10: Note: Live Balance figures are a manually-updated snapshot -- refresh them whenever you check statements, ideally at least quarterly, so Tab 3's projections start from an accurate baseline.
A11: Legend: pale-yellow cells are yours to type into; white cells hold formulas -- please don't overwrite them.

Sheet The_Refill_Engine
A1: Total Current Actual Wealth | B1: ='Account_Tracker'!$C$9
A2: Safety Anchor Target % (of Net Worth) | B2: 0.35
A3: Target Safety Anchor Balance ($) | B3: =B1*B2
A4: Sequence-of-Returns-Risk (SRR) Shield: the Safety Anchor Target % above controls how large a G Fund cash buffer this engine tries to maintain, so equities are never forced to sell at a loss to fund living expenses. Raise or lower it to fit your risk tolerance.
A6: THE QUARTERLY REFILL ENGINE — PRIMARY OUTPUT: RECOMMENDED TSP TOP-UP TRANSFER
A7: Year | B7: Quarter | C7: Quarterly Outflow (W_q) | D7: Annual Performance Signal | E7: G Fund Balance (Start of Qtr) | F7: Recommended Transfer This Quarter | G7: Actual Transferred (Log It Here) | H7: G Fund Balance (End of Qtr, Projected)
A8: 2026 | B8: Q1 | C8: =SUM('Variables_And_Log'!F3:H3) | D8: =E52 | E8: ='Account_Tracker'!$C$2 | F8: =IF(ISNUMBER(SEARCH("GOOD",D8)),MAX(0,$B$3-E8),0) | H8: =E8-C8+IF(G8="",F8,G8)
A9: 2026 | B9: Q2 | C9: =SUM('Variables_And_Log'!I3:K3) | D9: =E52 | E9: =H8 | F9: =IF(ISNUMBER(SEARCH("GOOD",D9)),MAX(0,$B$3-E9),0) | H9: =E9-C9+IF(G9="",F9,G9)
A10: 2026 | B10: Q3 | C10: =SUM('Variables_And_Log'!L3:N3) | D10: =E52 | E10: =H9 | F10: =IF(ISNUMBER(SEARCH("GOOD",D10)),MAX(0,$B$3-E10),0) | H10: =E10-C10+IF(G10="",F10,G10)
A11: 2026 | B11: Q4 | C11: =SUM('Variables_And_Log'!O3:Q3) | D11: =E52 | E11: =H10 | F11: =IF(ISNUMBER(SEARCH("GOOD",D11)),MAX(0,$B$3-E11),0) | H11: =E11-C11+IF(G11="",F11,G11)
A12: 2027 | B12: Q1 | C12: =SUM('Variables_And_Log'!F4:H4) | D12: =E53 | E12: =H11 | F12: =IF(ISNUMBER(SEARCH("GOOD",D12)),MAX(0,$B$3-E12),0) | H12: =E12-C12+IF(G12="",F12,G12)
A13: 2027 | B13: Q2 | C13: =SUM('Variables_And_Log'!I4:K4) | D13: =E53 | E13: =H12 | F13: =IF(ISNUMBER(SEARCH("GOOD",D13)),MAX(0,$B$3-E13),0) | H13: =E13-C13+IF(G13="",F13,G13)
A14: 2027 | B14: Q3 | C14: =SUM('Variables_And_Log'!L4:N4) | D14: =E53 | E14: =H13 | F14: =IF(ISNUMBER(SEARCH("GOOD",D14)),MAX(0,$B$3-E14),0) | H14: =E14-C14+IF(G14="",F14,G14)
A15: 2027 | B15: Q4 | C15: =SUM('Variables_And_Log'!O4:Q4) | D15: =E53 | E15: =H14 | F15: =IF(ISNUMBER(SEARCH("GOOD",D15)),MAX(0,$B$3-E15),0) | H15: =E15-C15+IF(G15="",F15,G15)
A16: 2028 | B16: Q1 | C16: =SUM('Variables_And_Log'!F5:H5) | D16: =E54 | E16: =H15 | F16: =IF(ISNUMBER(SEARCH("GOOD",D16)),MAX(0,$B$3-E16),0) | H16: =E16-C16+IF(G16="",F16,G16)
A17: 2028 | B17: Q2 | C17: =SUM('Variables_And_Log'!I5:K5) | D17: =E54 | E17: =H16 | F17: =IF(ISNUMBER(SEARCH("GOOD",D17)),MAX(0,$B$3-E17),0) | H17: =E17-C17+IF(G17="",F17,G17)
A18: 2028 | B18: Q3 | C18: =SUM('Variables_And_Log'!L5:N5) | D18: =E54 | E18: =H17 | F18: =IF(ISNUMBER(SEARCH("GOOD",D18)),MAX(0,$B$3-E18),0) | H18: =E18-C18+IF(G18="",F18,G18)
A19: 2028 | B19: Q4 | C19: =SUM('Variables_And_Log'!O5:Q5) | D19: =E54 | E19: =H18 | F19: =IF(ISNUMBER(SEARCH("GOOD",D19)),MAX(0,$B$3-E19),0) | H19: =E19-C19+IF(G19="",F19,G19)
A20: 2029 | B20: Q1 | C20: =SUM('Variables_And_Log'!F6:H6) | D20: =E55 | E20: =H19 | F20: =IF(ISNUMBER(SEARCH("GOOD",D20)),MAX(0,$B$3-E20),0) | H20: =E20-C20+IF(G20="",F20,G20)
A21: 2029 | B21: Q2 | C21: =SUM('Variables_And_Log'!I6:K6) | D21: =E55 | E21: =H20 | F21: =IF(ISNUMBER(SEARCH("GOOD",D21)),MAX(0,$B$3-E21),0) | H21: =E21-C21+IF(G21="",F21,G21)
A22: 2029 | B22: Q3 | C22: =SUM('Variables_And_Log'!L6:N6) | D22: =E55 | E22: =H21 | F22: =IF(ISNUMBER(SEARCH("GOOD",D22)),MAX(0,$B$3-E22),0) | H22: =E22-C22+IF(G22="",F22,G22)
A23: 2029 | B23: Q4 | C23: =SUM('Variables_And_Log'!O6:Q6) | D23: =E55 | E23: =H22 | F23: =IF(ISNUMBER(SEARCH("GOOD",D23)),MAX(0,$B$3-E23),0) | H23: =E23-C23+IF(G23="",F23,G23)
A24: 2030 | B24: Q1 | C24: =SUM('Variables_And_Log'!F7:H7) | D24: =E56 | E24: =H23 | F24: =IF(ISNUMBER(SEARCH("GOOD",D24)),MAX(0,$B$3-E24),0) | H24: =E24-C24+IF(G24="",F24,G24)
A25: 2030 | B25: Q2 | C25: =SUM('Variables_And_Log'!I7:K7) | D25: =E56 | E25: =H24 | F25: =IF(ISNUMBER(SEARCH("GOOD",D25)),MAX(0,$B$3-E25),0) | H25: =E25-C25+IF(G25="",F25,G25)
A26: 2030 | B26: Q3 | C26: =SUM('Variables_And_Log'!L7:N7) | D26: =E56 | E26: =H25 | F26: =IF(ISNUMBER(SEARCH("GOOD",D26)),MAX(0,$B$3-E26),0) | H26: =E26-C26+IF(G26="",F26,G26)
A27: 2030 | B27: Q4 | C27: =SUM('Variables_And_Log'!O7:Q7) | D27: =E56 | E27: =H26 | F27: =IF(ISNUMBER(SEARCH("GOOD",D27)),MAX(0,$B$3-E27),0) | H27: =E27-C27+IF(G27="",F27,G27)
A28: 2031 | B28: Q1 | C28: =SUM('Variables_And_Log'!F8:H8) | D28: =E57 | E28: =H27 | F28: =IF(ISNUMBER(SEARCH("GOOD",D28)),MAX(0,$B$3-E28),0) | H28: =E28-C28+IF(G28="",F28,G28)
A29: 2031 | B29: Q2 | C29: =SUM('Variables_And_Log'!I8:K8) | D29: =E57 | E29: =H28 | F29: =IF(ISNUMBER(SEARCH("GOOD",D29)),MAX(0,$B$3-E29),0) | H29: =E29-C29+IF(G29="",F29,G29)
A30: 2031 | B30: Q3 | C30: =SUM('Variables_And_Log'!L8:N8) | D30: =E57 | E30: =H29 | F30: =IF(ISNUMBER(SEARCH("GOOD",D30)),MAX(0,$B$3-E30),0) | H30: =E30-C30+IF(G30="",F30,G30)
A31: 2031 | B31: Q4 | C31: =SUM('Variables_And_Log'!O8:Q8) | D31: =E57 | E31: =H30 | F31: =IF(ISNUMBER(SEARCH("GOOD",D31)),MAX(0,$B$3-E31),0) | H31: =E31-C31+IF(G31="",F31,G31)
A32: 2032 | B32: Q1 | C32: =SUM('Variables_And_Log'!F9:H9) | D32: =E58 | E32: =H31 | F32: =IF(ISNUMBER(SEARCH("GOOD",D32)),MAX(0,$B$3-E32),0) | H32: =E32-C32+IF(G32="",F32,G32)
A33: 2032 | B33: Q2 | C33: =SUM('Variables_And_Log'!I9:K9) | D33: =E58 | E33: =H32 | F33: =IF(ISNUMBER(SEARCH("GOOD",D33)),MAX(0,$B$3-E33),0) | H33: =E33-C33+IF(G33="",F33,G33)
A34: 2032 | B34: Q3 | C34: =SUM('Variables_And_Log'!L9:N9) | D34: =E58 | E34: =H33 | F34: =IF(ISNUMBER(SEARCH("GOOD",D34)),MAX(0,$B$3-E34),0) | H34: =E34-C34+IF(G34="",F34,G34)
A35: 2032 | B35: Q4 | C35: =SUM('Variables_And_Log'!O9:Q9) | D35: =E58 | E35: =H34 | F35: =IF(ISNUMBER(SEARCH("GOOD",D35)),MAX(0,$B$3-E35),0) | H35: =E35-C35+IF(G35="",F35,G35)
A36: 2033 | B36: Q1 | C36: =SUM('Variables_And_Log'!F10:H10) | D36: =E59 | E36: =H35 | F36: =IF(ISNUMBER(SEARCH("GOOD",D36)),MAX(0,$B$3-E36),0) | H36: =E36-C36+IF(G36="",F36,G36)
A37: 2033 | B37: Q2 | C37: =SUM('Variables_And_Log'!I10:K10) | D37: =E59 | E37: =H36 | F37: =IF(ISNUMBER(SEARCH("GOOD",D37)),MAX(0,$B$3-E37),0) | H37: =E37-C37+IF(G37="",F37,G37)
A38: 2033 | B38: Q3 | C38: =SUM('Variables_And_Log'!L10:N10) | D38: =E59 | E38: =H37 | F38: =IF(ISNUMBER(SEARCH("GOOD",D38)),MAX(0,$B$3-E38),0) | H38: =E38-C38+IF(G38="",F38,G38)
A39: 2033 | B39: Q4 | C39: =SUM('Variables_And_Log'!O10:Q10) | D39: =E59 | E39: =H38 | F39: =IF(ISNUMBER(SEARCH("GOOD",D39)),MAX(0,$B$3-E39),0) | H39: =E39-C39+IF(G39="",F39,G39)
A40: 2034 | B40: Q1 | C40: =SUM('Variables_And_Log'!F11:H11) | D40: =E60 | E40: =H39 | F40: =IF(ISNUMBER(SEARCH("GOOD",D40)),MAX(0,$B$3-E40),0) | H40: =E40-C40+IF(G40="",F40,G40)
A41: 2034 | B41: Q2 | C41: =SUM('Variables_And_Log'!I11:K11) | D41: =E60 | E41: =H40 | F41: =IF(ISNUMBER(SEARCH("GOOD",D41)),MAX(0,$B$3-E41),0) | H41: =E41-C41+IF(G41="",F41,G41)
A42: 2034 | B42: Q3 | C42: =SUM('Variables_And_Log'!L11:N11) | D42: =E60 | E42: =H41 | F42: =IF(ISNUMBER(SEARCH("GOOD",D42)),MAX(0,$B$3-E42),0) | H42: =E42-C42+IF(G42="",F42,G42)
A43: 2034 | B43: Q4 | C43: =SUM('Variables_And_Log'!O11:Q11) | D43: =E60 | E43: =H42 | F43: =IF(ISNUMBER(SEARCH("GOOD",D43)),MAX(0,$B$3-E43),0) | H43: =E43-C43+IF(G43="",F43,G43)
A44: 2035 | B44: Q1 | C44: =SUM('Variables_And_Log'!F12:H12) | D44: =E61 | E44: =H43 | F44: =IF(ISNUMBER(SEARCH("GOOD",D44)),MAX(0,$B$3-E44),0) | H44: =E44-C44+IF(G44="",F44,G44)
A45: 2035 | B45: Q2 | C45: =SUM('Variables_And_Log'!I12:K12) | D45: =E61 | E45: =H44 | F45: =IF(ISNUMBER(SEARCH("GOOD",D45)),MAX(0,$B$3-E45),0) | H45: =E45-C45+IF(G45="",F45,G45)
A46: 2035 | B46: Q3 | C46: =SUM('Variables_And_Log'!L12:N12) | D46: =E61 | E46: =H45 | F46: =IF(ISNUMBER(SEARCH("GOOD",D46)),MAX(0,$B$3-E46),0) | H46: =E46-C46+IF(G46="",F46,G46)
A47: 2035 | B47: Q4 | C47: =SUM('Variables_And_Log'!O12:Q12) | D47: =E61 | E47: =H46 | F47: =IF(ISNUMBER(SEARCH("GOOD",D47)),MAX(0,$B$3-E47),0) | H47: =E47-C47+IF(G47="",F47,G47)
A50: ANNUAL SRR HURDLE MODEL — STRATEGIC PACING CHECK (GATES THE QUARTERLY REFILL ABOVE)
A51: Year | B51: Total Annual Hurdle Rate | C51: Annual Outflows (W_t) | D51: Simulated Target Portfolio (P_track) | E51: Performance Logic Trigger
A52: 2026 | B52: ='Variables_And_Log'!D3 | C52: ='Variables_And_Log'!E3 | D52: =ROUND(($B$1*B52)-C52,2) | E52: =IF(B$1>=D52,"✅ GOOD: Execute T2065 Rebalance & Rollover to TSP","⚠️ POOR: Freeze Equities. Draw Down G Fund")
A53: 2027 | B53: ='Variables_And_Log'!D4 | C53: ='Variables_And_Log'!E4 | D53: =ROUND((D52*B53)-C53,2) | E53: =IF(B$1>=D53,"✅ GOOD: Execute T2065 Rebalance & Rollover to TSP","⚠️ POOR: Freeze Equities. Draw Down G Fund")
A54: 2028 | B54: ='Variables_And_Log'!D5 | C54: ='Variables_And_Log'!E5 | D54: =ROUND((D53*B54)-C54,2) | E54: =IF(B$1>=D54,"✅ GOOD: Execute T2065 Rebalance & Rollover to TSP","⚠️ POOR: Freeze Equities. Draw Down G Fund")
A55: 2029 | B55: ='Variables_And_Log'!D6 | C55: ='Variables_And_Log'!E6 | D55: =ROUND((D54*B55)-C55,2) | E55: =IF(B$1>=D55,"✅ GOOD: Execute T2065 Rebalance & Rollover to TSP","⚠️ POOR: Freeze Equities. Draw Down G Fund")
A56: 2030 | B56: ='Variables_And_Log'!D7 | C56: ='Variables_And_Log'!E7 | D56: =ROUND((D55*B56)-C56,2) | E56: =IF(B$1>=D56,"✅ GOOD: Execute T2065 Rebalance & Rollover to TSP","⚠️ POOR: Freeze Equities. Draw Down G Fund")
A57: 2031 | B57: ='Variables_And_Log'!D8 | C57: ='Variables_And_Log'!E8 | D57: =ROUND((D56*B57)-C57,2) | E57: =IF(B$1>=D57,"✅ GOOD: Execute T2065 Rebalance & Rollover to TSP","⚠️ POOR: Freeze Equities. Draw Down G Fund")
A58: 2032 | B58: ='Variables_And_Log'!D9 | C58: ='Variables_And_Log'!E9 | D58: =ROUND((D57*B58)-C58,2) | E58: =IF(B$1>=D58,"✅ GOOD: Execute T2065 Rebalance & Rollover to TSP","⚠️ POOR: Freeze Equities. Draw Down G Fund")
A59: 2033 | B59: ='Variables_And_Log'!D10 | C59: ='Variables_And_Log'!E10 | D59: =ROUND((D58*B59)-C59,2) | E59: =IF(B$1>=D59,"✅ GOOD: Execute T2065 Rebalance & Rollover to TSP","⚠️ POOR: Freeze Equities. Draw Down G Fund")
A60: 2034 | B60: ='Variables_And_Log'!D11 | C60: ='Variables_And_Log'!E11 | D60: =ROUND((D59*B60)-C60,2) | E60: =IF(B$1>=D60,"✅ GOOD: Execute T2065 Rebalance & Rollover to TSP","⚠️ POOR: Freeze Equities. Draw Down G Fund")
A61: 2035 | B61: ='Variables_And_Log'!D12 | C61: ='Variables_And_Log'!E12 | D61: =ROUND((D60*B61)-C61,2) | E61: =IF(B$1>=D61,"✅ GOOD: Execute T2065 Rebalance & Rollover to TSP","⚠️ POOR: Freeze Equities. Draw Down G Fund")
A63: EXTRA CAPACITY INDICATORS
A64: Your Pre-Tax Rollover Conduit Capacity | B64: ='Account_Tracker'!$C$3 | C64: =IF(B64>0,"Conduit Open","Conduit Closed")
A66: TSP Cash Buffer Runway (Months) | B66: =IFERROR('Account_Tracker'!$C$2/AVERAGE('Variables_And_Log'!$F$3:$Q$3),"Log Monthly Payments to Calculate") | C66: =IF(ISNUMBER(B66),IF(B66>36,"Safe: 3+ Year Volatility Shield","Caution: Shield Shrinking"),"Awaiting Payment Data")
A67: (Runway uses the average of whichever 2026 monthly TSP payments you've logged so far.)
A69: EMERGENCY LIQUIDITY PROTOCOL — NEXT-DOLLAR PRIORITY ENGINE
A70: Next-Dollar Liquidity Priority | B70: =IF('Account_Tracker'!$C$2>0,"🛡️ SHIELD ACTIVE: Continue automated monthly draws directly from the TSP G Fund. Your equity engines are fully insulated from sequence-of-returns risk.",IF(AND('Account_Tracker'!$C$2=0,'Account_Tracker'!$C$8>0),"⚠️ SHIELD BROKEN: TSP G Fund is exhausted. IMMEDIATELY divert monthly checking draws to your Merrill Edge Cash Buffer. This buys next-day liquidity via Bank of America without forced retirement asset sales.",IF(AND('Account_Tracker'!$C$2=0,'Account_Tracker'!$C$8=0,'Account_Tracker'!$C$6>0),"🚨 EMERGENCY LIQUIDATION - STAGE 1: G Fund and Cash Buffers are exhausted. Turn on monthly distributions from Spouse's Current Employer 403b. Their pre-tax employer plan qualifies for the Maryland Pension Exclusion at age 65, making it more tax-efficient than touching your private traditional IRA.","💥 NUCLEAR PROTOCOL - STAGE 2: Absolute liquidity crisis. You are forced to break all shields. Begin selling shares of the 2065 Target Date Funds within your Private Traditional IRAs to fund monthly expenses. Maximize tax withholding at the time of distribution to shield your remaining capital from underpayment penalties.")))
A74: Legend: pale-yellow cells are yours to type into; white cells hold formulas -- please don't overwrite them.
